odoo/addons/account_invoice_import_facturae/README.rst
odoo/addons/account_invoice_import_facturae/__init__.py
odoo/addons/account_invoice_import_facturae/__manifest__.py
odoo/addons/account_invoice_import_facturae/data/Extension FACEB2B v1-1.xsd
odoo/addons/account_invoice_import_facturae/data/Facturaev3_2.xsd
odoo/addons/account_invoice_import_facturae/data/Facturaev3_2_1.xsd
odoo/addons/account_invoice_import_facturae/data/Facturaev3_2_1_wrapper.xsd
odoo/addons/account_invoice_import_facturae/data/FormatoXSD V1.0.xsd
odoo/addons/account_invoice_import_facturae/data/UtilitiesExtension.xsd
odoo/addons/account_invoice_import_facturae/data/xmldsig-core-schema.xsd
odoo/addons/account_invoice_import_facturae/i18n/account_invoice_import_facturae.pot
odoo/addons/account_invoice_import_facturae/readme/CONTRIBUTORS.rst
odoo/addons/account_invoice_import_facturae/readme/DESCRIPTION.rst
odoo/addons/account_invoice_import_facturae/readme/ROADMAP.rst
odoo/addons/account_invoice_import_facturae/readme/USAGE.rst
odoo/addons/account_invoice_import_facturae/static/description/icon.png
odoo/addons/account_invoice_import_facturae/static/description/index.html
odoo/addons/account_invoice_import_facturae/tests/__init__.py
odoo/addons/account_invoice_import_facturae/tests/test_import_facturae.py
odoo/addons/account_invoice_import_facturae/tests/files/facturae_01.xsig
odoo/addons/account_invoice_import_facturae/tests/files/facturae_02.xsig
odoo/addons/account_invoice_import_facturae/tests/files/facturae_03.xsig
odoo/addons/account_invoice_import_facturae/tests/files/facturae_04.xsig
odoo/addons/account_invoice_import_facturae/wizard/__init__.py
odoo/addons/account_invoice_import_facturae/wizard/account_invoice_import.py
odoo11_addon_account_invoice_import_facturae-11.0.1.0.0.99.dev5.dist-info/METADATA
odoo11_addon_account_invoice_import_facturae-11.0.1.0.0.99.dev5.dist-info/WHEEL
odoo11_addon_account_invoice_import_facturae-11.0.1.0.0.99.dev5.dist-info/top_level.txt
odoo11_addon_account_invoice_import_facturae-11.0.1.0.0.99.dev5.dist-info/RECORD
