Metadata-Version: 2.1
Name: odoo11-addon-account-invoice-import-facturae
Version: 11.0.1.0.0.99.dev5
Summary: Import supplier invoices/refunds in facturae format
Home-page: https://github.com/OCA/l10n-spain
Author: Creu Blanca, Odoo Community Association (OCA)
Author-email: support@odoo-community.org
License: AGPL-3
Platform: UNKNOWN
Classifier: Programming Language :: Python
Classifier: Framework :: Odoo
Classifier: Framework :: Odoo :: 11.0
Classifier: License :: OSI Approved :: GNU Affero General Public License v3
Requires-Python: >=2.7, !=3.0.*, !=3.1.*, !=3.2.*, !=3.3.*, !=3.4.*
Requires-Dist: odoo11-addon-account-invoice-import
Requires-Dist: odoo11-addon-base-iso3166
Requires-Dist: odoo <11.1dev,>=11.0a
Requires-Dist: xmlsig
